{
	"backtraceGraph" : 
	{
		"commands" : 
		[
			"install"
		],
		"files" : 
		[
			"external/glm/CMakeLists.txt"
		],
		"nodes" : 
		[
			{
				"file" : 0
			},
			{
				"command" : 0,
				"file" : 0,
				"line" : 176,
				"parent" : 0
			},
			{
				"command" : 0,
				"file" : 0,
				"line" : 193,
				"parent" : 0
			},
			{
				"command" : 0,
				"file" : 0,
				"line" : 209,
				"parent" : 0
			},
			{
				"command" : 0,
				"file" : 0,
				"line" : 218,
				"parent" : 0
			}
		]
	},
	"installers" : 
	[
		{
			"backtrace" : 1,
			"component" : "Unspecified",
			"destination" : "include",
			"paths" : 
			[
				"external/glm/glm"
			],
			"type" : "directory"
		},
		{
			"backtrace" : 2,
			"component" : "Unspecified",
			"destination" : "lib/cmake/glm",
			"paths" : 
			[
				"out/build/x64-Debug/external/glm/lib/cmake/glm/glmConfig.cmake",
				"out/build/x64-Debug/external/glm/glmConfigVersion.cmake"
			],
			"type" : "file"
		},
		{
			"backtrace" : 3,
			"component" : "Unspecified",
			"destination" : "lib/cmake/glm",
			"exportName" : "glmTargets",
			"exportTargets" : 
			[
				{
					"id" : "glm::@446904e9652187aa75c1",
					"index" : 0
				}
			],
			"paths" : 
			[
				"external/glm/CMakeFiles/Export/820b120f1c4a30a4249350d158e86720/glmTargets.cmake"
			],
			"type" : "export"
		},
		{
			"backtrace" : 4,
			"component" : "Unspecified",
			"destination" : "lib/pkgconfig",
			"paths" : 
			[
				"out/build/x64-Debug/external/glm/glm.pc"
			],
			"type" : "file"
		}
	],
	"paths" : 
	{
		"build" : "external/glm",
		"source" : "external/glm"
	}
}
